{
    "entries": [
        {
            "rank": 101,
            "teamId": "85510f58642e498ea2de33f7ad7517c1",
            "userName": "DEFFkid0225",
            "best_run": {
                "accuracy": 95,
                "score": 24277,
                "difficulty": 1,
                "instrument": 1,
                "stars": 4,
                "fullcombo": false
            },
            "sessions": [
                {
                    "time": 1730603417.024,
                    "valid": {
                        "accuracy": 95,
                        "score": 24277,
                        "difficulty": 1,
                        "instrument": 1,
                        "stars": 4,
                        "fullcombo": false
                    },
                    "stats": {
                        "band": {
                            "accuracy": 97,
                            "fullcombo": false,
                            "stars": 5,
                            "scores": {
                                "overdrive_bonus": 13391,
                                "base_score": 80539,
                                "total": 100721
                            }
                        },
                        "players": [
                            {
                                "accuracy": 99,
                                "score": 56261,
                                "difficulty": 2,
                                "instrument": 0,
                                "fullcombo": false,
                                "stars": 5,
                                "is_valid_entry": false
                            },
                            {
                                "accuracy": 95,
                                "score": 24277,
                                "difficulty": 1,
                                "instrument": 1,
                                "fullcombo": false,
                                "stars": 4,
                                "is_valid_entry": true
                            }
                        ]
                    }
                }
            ]
        },
        {
            "rank": 102,
            "teamId": "b74d814db8af45139d70cdab9f48d9ba",
            "userName": "Katiestrange",
            "best_run": {
                "accuracy": 99,
                "score": 23400,
                "difficulty": 0,
                "instrument": 1,
                "stars": 5,
                "fullcombo": false
            },
            "sessions": [
                {
                    "time": 1730648021.104,
                    "valid": {
                        "accuracy": 99,
                        "score": 23400,
                        "difficulty": 0,
                        "instrument": 1,
                        "stars": 5,
                        "fullcombo": false
                    },
                    "stats": {
                        "band": {
                            "accuracy": 99,
                            "fullcombo": false,
                            "stars": 4,
                            "scores": {
                                "overdrive_bonus": 0,
                                "base_score": 23400,
                                "total": 23400
                            }
                        },
                        "players": [
                            {
                                "accuracy": 99,
                                "score": 23400,
                                "difficulty": 0,
                                "instrument": 1,
                                "fullcombo": false,
                                "stars": 5,
                                "is_valid_entry": true
                            }
                        ]
                    }
                }
            ]
        },
        {
            "rank": 103,
            "teamId": "cdc3004088154867989f16317e75f19d",
            "userName": "Mamkim",
            "best_run": {
                "accuracy": 96,
                "score": 22302,
                "difficulty": 1,
                "instrument": 1,
                "stars": 4,
                "fullcombo": false
            },
            "sessions": [
                {
                    "time": 1730595494.291,
                    "valid": {
                        "accuracy": 96,
                        "score": 22302,
                        "difficulty": 1,
                        "instrument": 1,
                        "stars": 4,
                        "fullcombo": false
                    },
                    "stats": {
                        "band": {
                            "accuracy": 97,
                            "fullcombo": false,
                            "stars": 4,
                            "scores": {
                                "overdrive_bonus": 13907,
                                "base_score": 78877,
                                "total": 99454
                            }
                        },
                        "players": [
                            {
                                "accuracy": 96,
                                "score": 22302,
                                "difficulty": 1,
                                "instrument": 1,
                                "fullcombo": false,
                                "stars": 4,
                                "is_valid_entry": true
                            },
                            {
                                "accuracy": 98,
                                "score": 56575,
                                "difficulty": 1,
                                "instrument": 2,
                                "fullcombo": false,
                                "stars": 5,
                                "is_valid_entry": false
                            }
                        ]
                    }
                }
            ]
        },
        {
            "rank": 104,
            "teamId": "073b7cf342e1453ca3a5f4d1c4945b14",
            "userName": "Chrize",
            "best_run": {
                "accuracy": 98,
                "score": 21963,
                "difficulty": 0,
                "instrument": 1,
                "stars": 5,
                "fullcombo": false
            },
            "sessions": [
                {
                    "time": 1730745936.666,
                    "valid": {
                        "accuracy": 98,
                        "score": 21963,
                        "difficulty": 0,
                        "instrument": 1,
                        "stars": 5,
                        "fullcombo": false
                    },
                    "stats": {
                        "band": {
                            "accuracy": 98,
                            "fullcombo": false,
                            "stars": 4,
                            "scores": {
                                "overdrive_bonus": 0,
                                "base_score": 21963,
                                "total": 21963
                            }
                        },
                        "players": [
                            {
                                "accuracy": 98,
                                "score": 21963,
                                "difficulty": 0,
                                "instrument": 1,
                                "fullcombo": false,
                                "stars": 5,
                                "is_valid_entry": true
                            }
                        ]
                    }
                }
            ]
        },
        {
            "rank": 105,
            "teamId": "92f6eb88aad94f7ba46f91e132acdc87",
            "userName": "MoodyAddams007",
            "best_run": {
                "accuracy": 97,
                "score": 21539,
                "difficulty": 0,
                "instrument": 1,
                "stars": 5,
                "fullcombo": false
            },
            "sessions": [
                {
                    "time": 1730652631.33,
                    "valid": {
                        "accuracy": 97,
                        "score": 21539,
                        "difficulty": 0,
                        "instrument": 1,
                        "stars": 5,
                        "fullcombo": false
                    },
                    "stats": {
                        "band": {
                            "accuracy": 98,
                            "fullcombo": false,
                            "stars": 5,
                            "scores": {
                                "overdrive_bonus": 35035,
                                "base_score": 154954,
                                "total": 203035
                            }
                        },
                        "players": [
                            {
                                "accuracy": 97,
                                "score": 21539,
                                "difficulty": 0,
                                "instrument": 1,
                                "fullcombo": false,
                                "stars": 5,
                                "is_valid_entry": true
                            },
                            {
                                "accuracy": 99,
                                "score": 133414,
                                "difficulty": 2,
                                "instrument": 2,
                                "fullcombo": false,
                                "stars": 5,
                                "is_valid_entry": false
                            }
                        ]
                    }
                }
            ]
        },
        {
            "rank": 106,
            "teamId": "a52edb526958458e9ef323eaba58c4af",
            "userName": "Mxt\u0435o",
            "best_run": {
                "accuracy": 98,
                "score": 21280,
                "difficulty": 0,
                "instrument": 1,
                "stars": 5,
                "fullcombo": false
            },
            "sessions": [
                {
                    "time": 1730667441.862,
                    "valid": {
                        "accuracy": 98,
                        "score": 21280,
                        "difficulty": 0,
                        "instrument": 1,
                        "stars": 5,
                        "fullcombo": false
                    },
                    "stats": {
                        "band": {
                            "accuracy": 98,
                            "fullcombo": false,
                            "stars": 5,
                            "scores": {
                                "overdrive_bonus": 87926,
                                "base_score": 264678,
                                "total": 375053
                            }
                        },
                        "players": [
                            {
                                "accuracy": 99,
                                "score": 126435,
                                "difficulty": 2,
                                "instrument": 2,
                                "fullcombo": false,
                                "stars": 5,
                                "is_valid_entry": false
                            },
                            {
                                "accuracy": 98,
                                "score": 21280,
                                "difficulty": 0,
                                "instrument": 1,
                                "fullcombo": false,
                                "stars": 5,
                                "is_valid_entry": true
                            },
                            {
                                "accuracy": 99,
                                "score": 116962,
                                "difficulty": 2,
                                "instrument": 2,
                                "fullcombo": false,
                                "stars": 5,
                                "is_valid_entry": false
                            }
                        ]
                    }
                }
            ]
        },
        {
            "rank": 107,
            "teamId": "b1dcad3c1f70405eb0c6d5f7a56beb9e",
            "userName": "N0Ob.MaStEr_69.",
            "best_run": {
                "accuracy": 98,
                "score": 21189,
                "difficulty": 0,
                "instrument": 1,
                "stars": 5,
                "fullcombo": false
            },
            "sessions": [
                {
                    "time": 1730752477.465,
                    "valid": {
                        "accuracy": 98,
                        "score": 21189,
                        "difficulty": 0,
                        "instrument": 1,
                        "stars": 5,
                        "fullcombo": false
                    },
                    "stats": {
                        "band": {
                            "accuracy": 98,
                            "fullcombo": false,
                            "stars": 6,
                            "scores": {
                                "overdrive_bonus": 223206,
                                "base_score": 317456,
                                "total": 591857
                            }
                        },
                        "players": [
                            {
                                "accuracy": 99,
                                "score": 84162,
                                "difficulty": 3,
                                "instrument": 1,
                                "fullcombo": false,
                                "stars": 6,
                                "is_valid_entry": false
                            },
                            {
                                "accuracy": 98,
                                "score": 21189,
                                "difficulty": 0,
                                "instrument": 1,
                                "fullcombo": false,
                                "stars": 5,
                                "is_valid_entry": true
                            },
                            {
                                "accuracy": 98,
                                "score": 42131,
                                "difficulty": 1,
                                "instrument": 0,
                                "fullcombo": false,
                                "stars": 5,
                                "is_valid_entry": false
                            },
                            {
                                "accuracy": 99,
                                "score": 169972,
                                "difficulty": 3,
                                "instrument": 2,
                                "fullcombo": false,
                                "stars": 6,
                                "is_valid_entry": false
                            }
                        ]
                    }
                }
            ]
        },
        {
            "rank": 108,
            "teamId": "67ec313ab2a04db4b31b62082e94892d",
            "userName": "DoctaSleeps",
            "best_run": {
                "accuracy": 97,
                "score": 20072,
                "difficulty": 0,
                "instrument": 1,
                "stars": 5,
                "fullcombo": false
            },
            "sessions": [
                {
                    "time": 1730698614.759,
                    "valid": {
                        "accuracy": 97,
                        "score": 20072,
                        "difficulty": 0,
                        "instrument": 1,
                        "stars": 5,
                        "fullcombo": false
                    },
                    "stats": {
                        "band": {
                            "accuracy": 97,
                            "fullcombo": false,
                            "stars": 4,
                            "scores": {
                                "overdrive_bonus": 46775,
                                "base_score": 75862,
                                "total": 135258
                            }
                        },
                        "players": [
                            {
                                "accuracy": 97,
                                "score": 30043,
                                "difficulty": 0,
                                "instrument": 2,
                                "fullcombo": false,
                                "stars": 5,
                                "is_valid_entry": false
                            },
                            {
                                "accuracy": 97,
                                "score": 20072,
                                "difficulty": 0,
                                "instrument": 1,
                                "fullcombo": false,
                                "stars": 5,
                                "is_valid_entry": true
                            },
                            {
                                "accuracy": 99,
                                "score": 25746,
                                "difficulty": 0,
                                "instrument": 1,
                                "fullcombo": false,
                                "stars": 5,
                                "is_valid_entry": false
                            }
                        ]
                    }
                }
            ]
        },
        {
            "rank": 109,
            "teamId": "58165f202ec6403f88062835bf4dfe38",
            "userName": "Ezc1857",
            "best_run": {
                "accuracy": 91,
                "score": 19362,
                "difficulty": 2,
                "instrument": 1,
                "stars": 3,
                "fullcombo": false
            },
            "sessions": [
                {
                    "time": 1730612802.984,
                    "valid": {
                        "accuracy": 91,
                        "score": 19362,
                        "difficulty": 2,
                        "instrument": 1,
                        "stars": 3,
                        "fullcombo": false
                    },
                    "stats": {
                        "band": {
                            "accuracy": 89,
                            "fullcombo": false,
                            "stars": 2,
                            "scores": {
                                "overdrive_bonus": 16636,
                                "base_score": 87050,
                                "total": 119665
                            }
                        },
                        "players": [
                            {
                                "accuracy": 91,
                                "score": 19362,
                                "difficulty": 2,
                                "instrument": 1,
                                "fullcombo": false,
                                "stars": 3,
                                "is_valid_entry": true
                            },
                            {
                                "accuracy": 83,
                                "score": 26460,
                                "difficulty": 2,
                                "instrument": 3,
                                "fullcombo": false,
                                "stars": 2,
                                "is_valid_entry": false
                            },
                            {
                                "accuracy": 93,
                                "score": 41228,
                                "difficulty": 2,
                                "instrument": 2,
                                "fullcombo": false,
                                "stars": 3,
                                "is_valid_entry": false
                            }
                        ]
                    }
                }
            ]
        },
        {
            "rank": 110,
            "teamId": "e269a097d6704b0fa87a70790a8ffcbb",
            "userName": "WARMACHINE091815",
            "best_run": {
                "accuracy": 94,
                "score": 19293,
                "difficulty": 0,
                "instrument": 1,
                "stars": 5,
                "fullcombo": false
            },
            "sessions": [
                {
                    "time": 1730605510.391,
                    "valid": {
                        "accuracy": 94,
                        "score": 19293,
                        "difficulty": 0,
                        "instrument": 1,
                        "stars": 5,
                        "fullcombo": false
                    },
                    "stats": {
                        "band": {
                            "accuracy": 76,
                            "fullcombo": false,
                            "stars": 1,
                            "scores": {
                                "overdrive_bonus": 3252,
                                "base_score": 33183,
                                "total": 39409
                            }
                        },
                        "players": [
                            {
                                "accuracy": 94,
                                "score": 19293,
                                "difficulty": 0,
                                "instrument": 1,
                                "fullcombo": false,
                                "stars": 5,
                                "is_valid_entry": true
                            },
                            {
                                "accuracy": 59,
                                "score": 13889,
                                "difficulty": 3,
                                "instrument": 2,
                                "fullcombo": false,
                                "stars": 1,
                                "is_valid_entry": false
                            }
                        ]
                    }
                }
            ]
        },
        {
            "rank": 111,
            "teamId": "94f8c8672ec4466dbd3e34dad20daf5c",
            "userName": "GleamingBug2622",
            "best_run": {
                "accuracy": 97,
                "score": 18001,
                "difficulty": 1,
                "instrument": 1,
                "stars": 3,
                "fullcombo": false
            },
            "sessions": [
                {
                    "time": 1730662172.402,
                    "valid": {
                        "accuracy": 97,
                        "score": 18001,
                        "difficulty": 1,
                        "instrument": 1,
                        "stars": 3,
                        "fullcombo": false
                    },
                    "stats": {
                        "band": {
                            "accuracy": 96,
                            "fullcombo": false,
                            "stars": 4,
                            "scores": {
                                "overdrive_bonus": 7671,
                                "base_score": 61816,
                                "total": 81591
                            }
                        },
                        "players": [
                            {
                                "accuracy": 97,
                                "score": 18001,
                                "difficulty": 1,
                                "instrument": 1,
                                "fullcombo": false,
                                "stars": 3,
                                "is_valid_entry": true
                            },
                            {
                                "accuracy": 94,
                                "score": 11770,
                                "difficulty": 0,
                                "instrument": 3,
                                "fullcombo": false,
                                "stars": 3,
                                "is_valid_entry": false
                            },
                            {
                                "accuracy": 98,
                                "score": 32044,
                                "difficulty": 1,
                                "instrument": 0,
                                "fullcombo": false,
                                "stars": 5,
                                "is_valid_entry": false
                            }
                        ]
                    }
                }
            ]
        },
        {
            "rank": 112,
            "teamId": "ee15f76e789146928c9a4841a71615b9",
            "userName": "JJtheJamMan",
            "best_run": {
                "accuracy": 96,
                "score": 16216,
                "difficulty": 0,
                "instrument": 1,
                "stars": 4,
                "fullcombo": false
            },
            "sessions": [
                {
                    "time": 1730753889.663,
                    "valid": {
                        "accuracy": 96,
                        "score": 16216,
                        "difficulty": 0,
                        "instrument": 1,
                        "stars": 4,
                        "fullcombo": false
                    },
                    "stats": {
                        "band": {
                            "accuracy": 96,
                            "fullcombo": false,
                            "stars": 3,
                            "scores": {
                                "overdrive_bonus": 0,
                                "base_score": 16216,
                                "total": 16216
                            }
                        },
                        "players": [
                            {
                                "accuracy": 96,
                                "score": 16216,
                                "difficulty": 0,
                                "instrument": 1,
                                "fullcombo": false,
                                "stars": 4,
                                "is_valid_entry": true
                            }
                        ]
                    }
                }
            ]
        },
        {
            "rank": 113,
            "teamId": "c8bc8d3904a741f7948bd25bd9d82623",
            "userName": "CILLEY_FAMILY",
            "best_run": {
                "accuracy": 93,
                "score": 15882,
                "difficulty": 1,
                "instrument": 1,
                "stars": 3,
                "fullcombo": false
            },
            "sessions": [
                {
                    "time": 1730642698.513,
                    "valid": {
                        "accuracy": 93,
                        "score": 15882,
                        "difficulty": 1,
                        "instrument": 1,
                        "stars": 3,
                        "fullcombo": false
                    },
                    "stats": {
                        "band": {
                            "accuracy": 94,
                            "fullcombo": false,
                            "stars": 4,
                            "scores": {
                                "overdrive_bonus": 17619,
                                "base_score": 110220,
                                "total": 136636
                            }
                        },
                        "players": [
                            {
                                "accuracy": 93,
                                "score": 15882,
                                "difficulty": 1,
                                "instrument": 1,
                                "fullcombo": false,
                                "stars": 3,
                                "is_valid_entry": true
                            },
                            {
                                "accuracy": 96,
                                "score": 94338,
                                "difficulty": 3,
                                "instrument": 2,
                                "fullcombo": false,
                                "stars": 4,
                                "is_valid_entry": false
                            }
                        ]
                    }
                }
            ]
        },
        {
            "rank": 114,
            "teamId": "a7a927163da04a6bb3d15de9f12b3dbc",
            "userName": "juliasofi",
            "best_run": {
                "accuracy": 97,
                "score": 13815,
                "difficulty": 0,
                "instrument": 1,
                "stars": 4,
                "fullcombo": false
            },
            "sessions": [
                {
                    "time": 1730579562.859,
                    "valid": {
                        "accuracy": 97,
                        "score": 13815,
                        "difficulty": 0,
                        "instrument": 1,
                        "stars": 4,
                        "fullcombo": false
                    },
                    "stats": {
                        "band": {
                            "accuracy": 98,
                            "fullcombo": false,
                            "stars": 6,
                            "scores": {
                                "overdrive_bonus": 71786,
                                "base_score": 265450,
                                "total": 359539
                            }
                        },
                        "players": [
                            {
                                "accuracy": 97,
                                "score": 13815,
                                "difficulty": 0,
                                "instrument": 1,
                                "fullcombo": false,
                                "stars": 4,
                                "is_valid_entry": true
                            },
                            {
                                "accuracy": 99,
                                "score": 160670,
                                "difficulty": 3,
                                "instrument": 2,
                                "fullcombo": false,
                                "stars": 6,
                                "is_valid_entry": false
                            },
                            {
                                "accuracy": 100,
                                "score": 90964,
                                "difficulty": 3,
                                "instrument": 1,
                                "fullcombo": true,
                                "stars": 6,
                                "is_valid_entry": false
                            }
                        ]
                    }
                }
            ]
        },
        {
            "rank": 115,
            "teamId": "301f673e303746629ba5aa2a5283241e",
            "userName": "TACTICALTROOPER2",
            "best_run": {
                "accuracy": 96,
                "score": 13565,
                "difficulty": 0,
                "instrument": 1,
                "stars": 4,
                "fullcombo": false
            },
            "sessions": [
                {
                    "time": 1730595778.953,
                    "valid": {
                        "accuracy": 96,
                        "score": 13565,
                        "difficulty": 0,
                        "instrument": 1,
                        "stars": 4,
                        "fullcombo": false
                    },
                    "stats": {
                        "band": {
                            "accuracy": 94,
                            "fullcombo": false,
                            "stars": 2,
                            "scores": {
                                "overdrive_bonus": 4492,
                                "base_score": 25655,
                                "total": 30146
                            }
                        },
                        "players": [
                            {
                                "accuracy": 93,
                                "score": 12089,
                                "difficulty": 1,
                                "instrument": 1,
                                "fullcombo": false,
                                "stars": 2,
                                "is_valid_entry": false
                            },
                            {
                                "accuracy": 96,
                                "score": 13565,
                                "difficulty": 0,
                                "instrument": 1,
                                "fullcombo": false,
                                "stars": 4,
                                "is_valid_entry": true
                            }
                        ]
                    }
                }
            ]
        },
        {
            "rank": 116,
            "teamId": "6f42ec4cd5b44d06a4ea7f25e6447ada",
            "userName": "SOFTBALLscar25",
            "best_run": {
                "accuracy": 95,
                "score": 13159,
                "difficulty": 0,
                "instrument": 1,
                "stars": 3,
                "fullcombo": false
            },
            "sessions": [
                {
                    "time": 1730598903.557,
                    "valid": {
                        "accuracy": 95,
                        "score": 13159,
                        "difficulty": 0,
                        "instrument": 1,
                        "stars": 3,
                        "fullcombo": false
                    },
                    "stats": {
                        "band": {
                            "accuracy": 97,
                            "fullcombo": false,
                            "stars": 6,
                            "scores": {
                                "overdrive_bonus": 241788,
                                "base_score": 302047,
                                "total": 593949
                            }
                        },
                        "players": [
                            {
                                "accuracy": 98,
                                "score": 120979,
                                "difficulty": 3,
                                "instrument": 2,
                                "fullcombo": false,
                                "stars": 5,
                                "is_valid_entry": false
                            },
                            {
                                "accuracy": 98,
                                "score": 44978,
                                "difficulty": 2,
                                "instrument": 0,
                                "fullcombo": false,
                                "stars": 5,
                                "is_valid_entry": false
                            },
                            {
                                "accuracy": 95,
                                "score": 13159,
                                "difficulty": 0,
                                "instrument": 1,
                                "fullcombo": false,
                                "stars": 3,
                                "is_valid_entry": true
                            },
                            {
                                "accuracy": 98,
                                "score": 122930,
                                "difficulty": 3,
                                "instrument": 2,
                                "fullcombo": false,
                                "stars": 5,
                                "is_valid_entry": false
                            }
                        ]
                    }
                }
            ]
        },
        {
            "rank": 117,
            "teamId": "6fd12dc639cf4f56b0af1a8ecf2948e9",
            "userName": "GallantStand9204",
            "best_run": {
                "accuracy": 78,
                "score": 12389,
                "difficulty": 3,
                "instrument": 1,
                "stars": 2,
                "fullcombo": false
            },
            "sessions": [
                {
                    "time": 1730735921.419,
                    "valid": {
                        "accuracy": 78,
                        "score": 12389,
                        "difficulty": 3,
                        "instrument": 1,
                        "stars": 2,
                        "fullcombo": false
                    },
                    "stats": {
                        "band": {
                            "accuracy": 81,
                            "fullcombo": false,
                            "stars": 1,
                            "scores": {
                                "overdrive_bonus": 1275,
                                "base_score": 18485,
                                "total": 21524
                            }
                        },
                        "players": [
                            {
                                "accuracy": 85,
                                "score": 6096,
                                "difficulty": 0,
                                "instrument": 2,
                                "fullcombo": false,
                                "stars": 2,
                                "is_valid_entry": false
                            },
                            {
                                "accuracy": 78,
                                "score": 12389,
                                "difficulty": 3,
                                "instrument": 1,
                                "fullcombo": false,
                                "stars": 2,
                                "is_valid_entry": true
                            }
                        ]
                    }
                }
            ]
        },
        {
            "rank": 118,
            "teamId": "a0f8273ccd9246428617f0188a328fc0",
            "userName": "BigPanda0709",
            "best_run": {
                "accuracy": 93,
                "score": 12089,
                "difficulty": 1,
                "instrument": 1,
                "stars": 2,
                "fullcombo": false
            },
            "sessions": [
                {
                    "time": 1730595778.953,
                    "valid": {
                        "accuracy": 93,
                        "score": 12089,
                        "difficulty": 1,
                        "instrument": 1,
                        "stars": 2,
                        "fullcombo": false
                    },
                    "stats": {
                        "band": {
                            "accuracy": 94,
                            "fullcombo": false,
                            "stars": 2,
                            "scores": {
                                "overdrive_bonus": 4492,
                                "base_score": 25655,
                                "total": 30146
                            }
                        },
                        "players": [
                            {
                                "accuracy": 93,
                                "score": 12089,
                                "difficulty": 1,
                                "instrument": 1,
                                "fullcombo": false,
                                "stars": 2,
                                "is_valid_entry": true
                            },
                            {
                                "accuracy": 96,
                                "score": 13565,
                                "difficulty": 0,
                                "instrument": 1,
                                "fullcombo": false,
                                "stars": 4,
                                "is_valid_entry": false
                            }
                        ]
                    }
                }
            ]
        },
        {
            "rank": 119,
            "teamId": "ae73ecb443b3441186a0d3f53d36b27c",
            "userName": "TheDBZnerd",
            "best_run": {
                "accuracy": 88,
                "score": 11312,
                "difficulty": 1,
                "instrument": 1,
                "stars": 2,
                "fullcombo": false
            },
            "sessions": [
                {
                    "time": 1730722065.544,
                    "valid": {
                        "accuracy": 88,
                        "score": 11312,
                        "difficulty": 1,
                        "instrument": 1,
                        "stars": 2,
                        "fullcombo": false
                    },
                    "stats": {
                        "band": {
                            "accuracy": 94,
                            "fullcombo": false,
                            "stars": 3,
                            "scores": {
                                "overdrive_bonus": 4704,
                                "base_score": 21330,
                                "total": 27975
                            }
                        },
                        "players": [
                            {
                                "accuracy": 88,
                                "score": 11312,
                                "difficulty": 1,
                                "instrument": 1,
                                "fullcombo": false,
                                "stars": 2,
                                "is_valid_entry": true
                            },
                            {
                                "accuracy": 100,
                                "score": 10017,
                                "difficulty": 0,
                                "instrument": 0,
                                "fullcombo": false,
                                "stars": 5,
                                "is_valid_entry": false
                            }
                        ]
                    }
                }
            ]
        },
        {
            "rank": 120,
            "teamId": "3e295e416ee046bb89c3591100294b10",
            "userName": "mikey123122",
            "best_run": {
                "accuracy": 41,
                "score": 3907,
                "difficulty": 0,
                "instrument": 1,
                "stars": 1,
                "fullcombo": false
            },
            "sessions": [
                {
                    "time": 1730662279.255,
                    "valid": {
                        "accuracy": 41,
                        "score": 3907,
                        "difficulty": 0,
                        "instrument": 1,
                        "stars": 1,
                        "fullcombo": false
                    },
                    "stats": {
                        "band": {
                            "accuracy": 79,
                            "fullcombo": false,
                            "stars": 5,
                            "scores": {
                                "overdrive_bonus": 74943,
                                "base_score": 211376,
                                "total": 321993
                            }
                        },
                        "players": [
                            {
                                "accuracy": 41,
                                "score": 3907,
                                "difficulty": 0,
                                "instrument": 1,
                                "fullcombo": false,
                                "stars": 1,
                                "is_valid_entry": true
                            },
                            {
                                "accuracy": 99,
                                "score": 64740,
                                "difficulty": 1,
                                "instrument": 3,
                                "fullcombo": false,
                                "stars": 5,
                                "is_valid_entry": false
                            },
                            {
                                "accuracy": 99,
                                "score": 142729,
                                "difficulty": 3,
                                "instrument": 2,
                                "fullcombo": false,
                                "stars": 6,
                                "is_valid_entry": false
                            }
                        ]
                    }
                }
            ]
        },
        {
            "rank": 121,
            "teamId": "a2b3af4993904e38816339cff282ce7d",
            "userName": "CheeznipCJ",
            "best_run": {
                "accuracy": 55,
                "score": 2943,
                "difficulty": 0,
                "instrument": 1,
                "stars": 1,
                "fullcombo": false
            },
            "sessions": [
                {
                    "time": 1730614620.035,
                    "valid": {
                        "accuracy": 55,
                        "score": 2943,
                        "difficulty": 0,
                        "instrument": 1,
                        "stars": 1,
                        "fullcombo": false
                    },
                    "stats": {
                        "band": {
                            "accuracy": 51,
                            "fullcombo": false,
                            "stars": 4,
                            "scores": {
                                "overdrive_bonus": 654,
                                "base_score": 81983,
                                "total": 96181
                            }
                        },
                        "players": [
                            {
                                "accuracy": 0,
                                "score": 0,
                                "difficulty": 0,
                                "instrument": 4,
                                "fullcombo": false,
                                "stars": 0,
                                "is_valid_entry": false
                            },
                            {
                                "accuracy": 55,
                                "score": 2943,
                                "difficulty": 0,
                                "instrument": 1,
                                "fullcombo": false,
                                "stars": 1,
                                "is_valid_entry": true
                            },
                            {
                                "accuracy": 100,
                                "score": 79040,
                                "difficulty": 1,
                                "instrument": 3,
                                "fullcombo": false,
                                "stars": 5,
                                "is_valid_entry": false
                            }
                        ]
                    }
                }
            ]
        },
        {
            "rank": 122,
            "teamId": "5949a759f83e48fcaa0b469a5e018e89",
            "userName": "santithegoat21",
            "best_run": {
                "accuracy": 47,
                "score": 2258,
                "difficulty": 0,
                "instrument": 1,
                "stars": 1,
                "fullcombo": false
            },
            "sessions": [
                {
                    "time": 1730563966.925,
                    "valid": {
                        "accuracy": 47,
                        "score": 2258,
                        "difficulty": 0,
                        "instrument": 1,
                        "stars": 1,
                        "fullcombo": false
                    },
                    "stats": {
                        "band": {
                            "accuracy": 71,
                            "fullcombo": false,
                            "stars": 2,
                            "scores": {
                                "overdrive_bonus": 260,
                                "base_score": 41367,
                                "total": 45090
                            }
                        },
                        "players": [
                            {
                                "accuracy": 47,
                                "score": 2258,
                                "difficulty": 0,
                                "instrument": 1,
                                "fullcombo": false,
                                "stars": 1,
                                "is_valid_entry": true
                            },
                            {
                                "accuracy": 96,
                                "score": 39109,
                                "difficulty": 1,
                                "instrument": 2,
                                "fullcombo": false,
                                "stars": 4,
                                "is_valid_entry": false
                            }
                        ]
                    }
                }
            ]
        },
        {
            "rank": 123,
            "teamId": "c338fb85538343fb9d7707d478a3016d",
            "userName": "YahirIsAwesome",
            "best_run": {
                "accuracy": 0,
                "score": 0,
                "difficulty": 2,
                "instrument": 1,
                "stars": 0,
                "fullcombo": false
            },
            "sessions": [
                {
                    "time": 1730580943.488,
                    "valid": {
                        "accuracy": 0,
                        "score": 0,
                        "difficulty": 2,
                        "instrument": 1,
                        "stars": 0,
                        "fullcombo": false
                    },
                    "stats": {
                        "band": {
                            "accuracy": 0,
                            "fullcombo": false,
                            "stars": 0,
                            "scores": {
                                "overdrive_bonus": 0,
                                "base_score": 0,
                                "total": 0
                            }
                        },
                        "players": [
                            {
                                "accuracy": 0,
                                "score": 0,
                                "difficulty": 2,
                                "instrument": 1,
                                "fullcombo": false,
                                "stars": 0,
                                "is_valid_entry": true
                            }
                        ]
                    }
                }
            ]
        },
        {
            "rank": 124,
            "teamId": "8b2e8391ec60479ea074da613784e000",
            "userName": "Jody2Jodeci \u1d57\u1d57\u1d5b",
            "best_run": {
                "accuracy": 0,
                "score": 0,
                "difficulty": 0,
                "instrument": 1,
                "stars": 0,
                "fullcombo": false
            },
            "sessions": [
                {
                    "time": 1730630588.407,
                    "valid": {
                        "accuracy": 0,
                        "score": 0,
                        "difficulty": 0,
                        "instrument": 1,
                        "stars": 0,
                        "fullcombo": false
                    },
                    "stats": {
                        "band": {
                            "accuracy": 25,
                            "fullcombo": false,
                            "stars": 1,
                            "scores": {
                                "overdrive_bonus": 0,
                                "base_score": 43506,
                                "total": 51206
                            }
                        },
                        "players": [
                            {
                                "accuracy": 0,
                                "score": 0,
                                "difficulty": 0,
                                "instrument": 1,
                                "fullcombo": false,
                                "stars": 0,
                                "is_valid_entry": true
                            },
                            {
                                "accuracy": 0,
                                "score": 0,
                                "difficulty": 3,
                                "instrument": 4,
                                "fullcombo": false,
                                "stars": 0,
                                "is_valid_entry": false
                            },
                            {
                                "accuracy": 75,
                                "score": 43506,
                                "difficulty": 2,
                                "instrument": 2,
                                "fullcombo": false,
                                "stars": 3,
                                "is_valid_entry": false
                            }
                        ]
                    }
                }
            ]
        }
    ]
}